image_processing_alisson/__init__.py
image_processing_alisson/processing/__init__.py
image_processing_alisson/processing/combination.py
image_processing_alisson/processing/transformation.py
image_processing_alisson/utils/__init__.py
image_processing_alisson/utils/io.py
image_processing_alisson/utils/plot.py
image_processing_alisson-0.0.1.dist-info/METADATA
image_processing_alisson-0.0.1.dist-info/WHEEL
image_processing_alisson-0.0.1.dist-info/top_level.txt
image_processing_alisson-0.0.1.dist-info/RECORD
