Metadata-Version: 2.1
Name: image-processing-alisson
Version: 0.0.1
Summary: Image Processing Package using Skimage
Home-page: https://github.com/alissonwr/Desafios_Ntt_Data_Dio/tree/1bfc7e799f6ae9519bec3bf8c668cda0931e30ec/image-processing-package
Author: Alisson
Requires-Python: >=3.5
Requires-Dist: matplotlib
Requires-Dist: numpy
Requires-Dist: scikit-image >=0.16.1
